LICENSE
README.md
setup.py
pottery/__init__.py
pottery/aionextid.py
pottery/aioredlock.py
pottery/annotations.py
pottery/base.py
pottery/bloom.py
pottery/cache.py
pottery/counter.py
pottery/deque.py
pottery/dict.py
pottery/exceptions.py
pottery/executor.py
pottery/hyper.py
pottery/list.py
pottery/monkey.py
pottery/nextid.py
pottery/py.typed
pottery/queue.py
pottery/redlock.py
pottery/set.py
pottery/timer.py
pottery_prod.egg-info/PKG-INFO
pottery_prod.egg-info/SOURCES.txt
pottery_prod.egg-info/dependency_links.txt
pottery_prod.egg-info/requires.txt
pottery_prod.egg-info/top_level.txt
tests/test_aionextid.py
tests/test_aioredlock.py
tests/test_base.py
tests/test_bloom.py
tests/test_cache.py
tests/test_counter.py
tests/test_deque.py
tests/test_dict.py
tests/test_doctests.py
tests/test_executor.py
tests/test_hyper.py
tests/test_list.py
tests/test_monkey.py
tests/test_nextid.py
tests/test_queue.py
tests/test_redlock.py
tests/test_set.py
tests/test_timer.py