Metadata-Version: 2.1
Name: pottery-prod
Version: 3.0.0
Summary: Redis is awesome, but Redis commands are not always intuitive.  Pottery is a
Home-page: https://github.com/brainix/pottery
Author: Rajiv Bakulesh Shah
Author-email: brainix@gmail.com
License: Apache 2.0
Keywords: Redis client persistent storage
Classifier: License :: OSI Approved :: Apache Software License
Classifier: Intended Audience :: Developers
Classifier: Natural Language :: English
Classifier: Development Status :: 4 - Beta
Classifier: Topic :: Database :: Front-Ends
Classifier: Topic :: System :: Distributed Computing
Classifier: Topic :: Utilities
Classifier: Programming Language :: Python :: 3 :: Only
Classifier: Programming Language :: Python :: 3.7
Classifier: Programming Language :: Python :: 3.8
Classifier: Programming Language :: Python :: 3.9
Classifier: Programming Language :: Python :: 3.10
Classifier: Framework :: AsyncIO
Classifier: Typing :: Typed
Requires-Python: >=3.7, <4
License-File: LICENSE
